django_flatpages_x-0.1.5.dist-info/DESCRIPTION.rst
django_flatpages_x-0.1.5.dist-info/METADATA
django_flatpages_x-0.1.5.dist-info/RECORD
django_flatpages_x-0.1.5.dist-info/WHEEL
django_flatpages_x-0.1.5.dist-info/metadata.json
django_flatpages_x-0.1.5.dist-info/top_level.txt
flatpages_x/__init__.py
flatpages_x/admin.py
flatpages_x/markdown_parser.py
flatpages_x/models.py
flatpages_x/settings.py
flatpages_x/tests.py
flatpages_x/utils.py
flatpages_x/fixtures/test_data.json
flatpages_x/migrations/0001_initial.py
flatpages_x/migrations/__init__.py
flatpages_x/templates/flatpages_x/_metatag_snippet.html
flatpages_x/templatetags/__init__.py
flatpages_x/templatetags/flatpages_x_tags.py
