Metadata-Version: 2.0
Name: django-flatpages-x
Version: 0.1.5
Summary: Some Basic extensions for django-contrib-flatpages
Home-page: http://github.com/chrisdev/django-flatpages-x
Author: Chris Clarke
Author-email: cclarke@chrisdev.com
License: MIT
Platform: UNKNOWN
Classifier: Development Status :: 3 - Alpha
Classifier: Environment :: Web Environment
Classifier: Intended Audience :: Developers
Classifier: License :: OSI Approved :: BSD License
Classifier: Operating System :: OS Independent
Classifier: Programming Language :: Python
Classifier: Framework :: Django
